WuyunZhishikuDisiBufen/README.md
WuyunZhishikuDisiBufen/__init__.py
WuyunZhishikuDisiBufen/__main__.py
WuyunZhishikuDisiBufen/file.epub
WuyunZhishikuDisiBufen/index.html
WuyunZhishikuDisiBufen/css/__init__.py
WuyunZhishikuDisiBufen/css/annotations.css
WuyunZhishikuDisiBufen/css/main.css
WuyunZhishikuDisiBufen/css/normalize.css
WuyunZhishikuDisiBufen/css/popup.css
WuyunZhishikuDisiBufen/font/__init__.py
WuyunZhishikuDisiBufen/font/fontello.eot
WuyunZhishikuDisiBufen/font/fontello.svg
WuyunZhishikuDisiBufen/font/fontello.ttf
WuyunZhishikuDisiBufen/font/fontello.woff
WuyunZhishikuDisiBufen/img/__init__.py
WuyunZhishikuDisiBufen/img/annotator-glyph-sprite.png
WuyunZhishikuDisiBufen/img/annotator-icon-sprite.png
WuyunZhishikuDisiBufen/img/apple-touch-icon.png
WuyunZhishikuDisiBufen/img/cancelfullscreen.png
WuyunZhishikuDisiBufen/img/close.png
WuyunZhishikuDisiBufen/img/fullscreen.png
WuyunZhishikuDisiBufen/img/loader.gif
WuyunZhishikuDisiBufen/img/menu-icon.png
WuyunZhishikuDisiBufen/img/save.png
WuyunZhishikuDisiBufen/img/saved.png
WuyunZhishikuDisiBufen/img/settings-s.png
WuyunZhishikuDisiBufen/img/settings.png
WuyunZhishikuDisiBufen/img/star.png
WuyunZhishikuDisiBufen/js/__init__.py
WuyunZhishikuDisiBufen/js/epub.js
WuyunZhishikuDisiBufen/js/epub.min.js
WuyunZhishikuDisiBufen/js/epub.min.map
WuyunZhishikuDisiBufen/js/hooks.min.js
WuyunZhishikuDisiBufen/js/hooks.min.map
WuyunZhishikuDisiBufen/js/reader.js
WuyunZhishikuDisiBufen/js/reader.js.map
WuyunZhishikuDisiBufen/js/reader.min.js
WuyunZhishikuDisiBufen/js/reader.min.map
WuyunZhishikuDisiBufen/js/hooks/__init__.py
WuyunZhishikuDisiBufen/js/hooks/extensions/__init__.py
WuyunZhishikuDisiBufen/js/hooks/extensions/highlight.js
WuyunZhishikuDisiBufen/js/libs/__init__.py
WuyunZhishikuDisiBufen/js/libs/jquery.min.js
WuyunZhishikuDisiBufen/js/libs/localforage.min.js
WuyunZhishikuDisiBufen/js/libs/screenfull.js
WuyunZhishikuDisiBufen/js/libs/screenfull.min.js
WuyunZhishikuDisiBufen/js/libs/zip.min.js
wuyun_zhishiku_disi_bufen-2024.3.5.0.dist-info/METADATA
wuyun_zhishiku_disi_bufen-2024.3.5.0.dist-info/WHEEL
wuyun_zhishiku_disi_bufen-2024.3.5.0.dist-info/entry_points.txt
wuyun_zhishiku_disi_bufen-2024.3.5.0.dist-info/top_level.txt
wuyun_zhishiku_disi_bufen-2024.3.5.0.dist-info/RECORD
